pigeonX/run.py
pigeonX-0.0.2.dist-info/METADATA
pigeonX-0.0.2.dist-info/WHEEL
pigeonX-0.0.2.dist-info/top_level.txt
pigeonX-0.0.2.dist-info/RECORD
