Metadata-Version: 2.1
Name: pigeonX
Version: 0.0.2
Requires-Dist: requests
